finsh/__init__.py
finsh/__main__.py
finsh/finsh.py
finsh/manage.py
finsh/sad/__init__.py
finsh/sad/asgi.py
finsh/sad/conf.py
finsh/sad/core.py
finsh/sad/settings.py
finsh/sad/urls.py
finsh/sad/wsgi.py
finsh/shareing/__init__.py
finsh/shareing/apps.py
finsh/shareing/directoring.py
finsh/shareing/views.py
finsh-0.1.4.dist-info/LICENSE
finsh-0.1.4.dist-info/METADATA
finsh-0.1.4.dist-info/WHEEL
finsh-0.1.4.dist-info/top_level.txt
finsh-0.1.4.dist-info/RECORD
