Metadata-Version: 2.1
Name: finsh
Version: 0.1.4
Summary: Share files using django
Home-page: https://github.com/mohali4/finsh
Author: mohali hamilton
Author-email: mahmohamad560@gmail.com
License: MIT
License-File: LICENSE
Requires-Dist: django
Requires-Dist: requests
Requires-Dist: termcolor
